voted_ranking/__init__.py
voted_ranking/model/__init__.py
voted_ranking/model/base.py
voted_ranking/model/bayesian.py
voted_ranking/model/hackernews.py
voted_ranking/model/model.py
voted_ranking/model/newton.py
voted_ranking/model/reddit.py
voted_ranking/model/wilson.py
voted_ranking-0.1.6.dist-info/METADATA
voted_ranking-0.1.6.dist-info/WHEEL
voted_ranking-0.1.6.dist-info/entry_points.txt
voted_ranking-0.1.6.dist-info/top_level.txt
voted_ranking-0.1.6.dist-info/RECORD
