Metadata-Version: 2.1
Name: voted-ranking
Version: 0.1.6
Summary: UNKNOWN
Home-page: UNKNOWN
Author: Guokr Inc.
Author-email: jinyang.zhou@guokr.com
License: UNKNOWN
Platform: UNKNOWN
Classifier: Programming Language :: Python :: 2.7
Classifier: License :: OSI Approved :: MIT License
Classifier: Topic :: Text Processing
Classifier: Topic :: Text Processing :: Indexing
Classifier: Topic :: Text Processing :: Linguistic
Requires-Dist: arrow
